[
    {
        "id": 1,
        "title": "将满70岁的法院原审判员退休20多年被查，专家：退休不等于进保险箱",
        "desc": "对于刘其祥退休20多年还被查，北京师范大学国际反腐败教育与研究中心主任彭新林接受红星新闻记者采访时表示，退休20多年被查，这再次表明了退休不等于“平安着陆”，反腐从来不存在既往不咎。",
        "image": "https://k.sinaimg.cn/n/spider20230525/298/w1618h1080/20230525/2c9f-a44b25ca79079bffc5b03f00b68c86da.jpg/w700d1q75cms.jpg?by=cms_fixed_width"
    },
    {
        "id": 2,
        "title": "风波中的国泰航空：多次名列民航局境外航司投诉量榜首，去年载客量较2019年缩水九成",
        "desc": "近日，国泰航空（0293.HK，股价7.5港元，市值482.79亿港元）歧视非英语乘客的风波愈演愈烈，公司两日内三度道歉，香港特别行政区行政长官李家超也表示痛心。",
        "image": "https://k.sinaimg.cn/n/news/crawl/117/w550h367/20230525/e348-558b8c193f5888e66b50bc0ab4175238.jpg/w700d1q75cms.jpg?by=cms_fixed_width"
    },
    {
        "id": 3,
        "title": "习近平出席欧亚经济联盟第二届欧亚经济论坛全会开幕式并致辞",
        "desc": "新华社北京5月24日电 5月24日，国家主席习近平应邀以视频方式出席欧亚经济联盟第二届欧亚经济论坛全会开幕式并致辞。",
        "image": "https://k.sinaimg.cn/n/default/crawl/128/w550h378/20230525/c020-942b00002acf8d3ed001fb957bace000.jpg/w700d1q75cms.jpg?by=cms_fixed_width"
    },
    {
        "id": 4,
        "title": "瞭望丨建设更高水平开放型经济新体制",
        "desc": "构建开放型经济新体制，是以习近平同志为核心的党中央提出的具有原创性、时代性的概念和理论。其基本内涵可概括为四方面，即建立市场配置资源新机制、形成经济运行管理新模式、形成全方位开放新格局、形成国际合作竞争新优势。",
        "image": "https://k.sinaimg.cn/n/news/crawl/112/w550h362/20230524/5c2b-f3e6a759591b4cdcd02ebdc7b050ede3.png/w700d1q75cms.jpg?by=cms_fixed_width"
    }
]